setup.py
BackTranslate.egg-info/PKG-INFO
BackTranslate.egg-info/SOURCES.txt
BackTranslate.egg-info/dependency_links.txt
BackTranslate.egg-info/entry_points.txt
BackTranslate.egg-info/requires.txt
BackTranslate.egg-info/top_level.txt
backtranslate/__init__.py
backtranslate/backtranslate.py
backtranslate/cli.py
backtranslate/util.py